Metadata-Version: 2.1
Name: Dev-sanduicheira
Version: 1.0
Summary: Este pacote irá fornecer ferramentas para manusear sua sanduicheira intelijegue
Author: Luiz
Author-email: luiz@example.com
Keywords: sanduicheira,automatizar
License-File: license.txt
